pytest_finer_verdicts/__init__.py
pytest_finer_verdicts/plugin.py
pytest_finer_verdicts-1.0.6.post1.dist-info/LICENSE.txt
pytest_finer_verdicts-1.0.6.post1.dist-info/METADATA
pytest_finer_verdicts-1.0.6.post1.dist-info/WHEEL
pytest_finer_verdicts-1.0.6.post1.dist-info/entry_points.txt
pytest_finer_verdicts-1.0.6.post1.dist-info/top_level.txt
pytest_finer_verdicts-1.0.6.post1.dist-info/RECORD
