Metadata-Version: 2.1
Name: pytest-finer-verdicts
Version: 1.0.6.post1
Summary: A pytest plugin to treat non-assertion failures as test errors.
Home-page: https://github.com/rvprasad/pytest-finer-verdicts
Author: Venkatesh-Prasad Ranganath
Author-email: UNKNOWN
License: BSD 3-Clause License
Download-URL: https://github.com/rvprasad/pytest-finer-verdicts/archive/v1.0.6.zip
Keywords: testing,pytest,verdict
Platform: unix
Platform: linux
Platform: osx
Platform: cygwin
Platform: win32
Classifier: Intended Audience :: Developers
Classifier: Topic :: Software Development :: Testing
Classifier: Operating System :: OS Independent
Classifier: Programming Language :: Python
Classifier: Programming Language :: Python :: 3.8
Requires-Dist: pytest (>=5.4.3)
